odoo/addons/account_credit_control_queue_job/README.rst
odoo/addons/account_credit_control_queue_job/__init__.py
odoo/addons/account_credit_control_queue_job/__manifest__.py
odoo/addons/account_credit_control_queue_job/i18n/account_credit_control_queue_job.pot
odoo/addons/account_credit_control_queue_job/i18n/pt.po
odoo/addons/account_credit_control_queue_job/i18n/pt_BR.po
odoo/addons/account_credit_control_queue_job/models/__init__.py
odoo/addons/account_credit_control_queue_job/models/credit_control_line.py
odoo/addons/account_credit_control_queue_job/readme/CONTRIBUTORS.rst
odoo/addons/account_credit_control_queue_job/readme/DESCRIPTION.rst
odoo/addons/account_credit_control_queue_job/readme/USAGE.rst
odoo/addons/account_credit_control_queue_job/static/description/icon.png
odoo/addons/account_credit_control_queue_job/static/description/index.html
odoo/addons/account_credit_control_queue_job/tests/__init__.py
odoo/addons/account_credit_control_queue_job/tests/test_credit_control_emailer.py
odoo/addons/account_credit_control_queue_job/wizard/__init__.py
odoo/addons/account_credit_control_queue_job/wizard/credit_control_communication.py
odoo/addons/account_credit_control_queue_job/wizard/credit_control_emailer.py
odoo/addons/account_credit_control_queue_job/wizard/credit_control_emailer_view.xml
odoo12_addon_account_credit_control_queue_job-12.0.2.0.0.dist-info/METADATA
odoo12_addon_account_credit_control_queue_job-12.0.2.0.0.dist-info/WHEEL
odoo12_addon_account_credit_control_queue_job-12.0.2.0.0.dist-info/top_level.txt
odoo12_addon_account_credit_control_queue_job-12.0.2.0.0.dist-info/RECORD
