Metadata-Version: 2.1
Name: odoo12-addon-account-credit-control-queue-job
Version: 12.0.2.0.0
Summary: This addon adds the opportunity to run some credit control tasks in jobs
Home-page: https://github.com/OCA/credit-control
Author: ACSONE SA/NV,Odoo Community Association (OCA)
Author-email: support@odoo-community.org
License: AGPL-3
Platform: UNKNOWN
Classifier: Programming Language :: Python
Classifier: Framework :: Odoo
Classifier: License :: OSI Approved :: GNU Affero General Public License v3
Requires-Python: >=3.5
Requires-Dist: odoo12-addon-account-credit-control
Requires-Dist: odoo12-addon-queue-job-batch
Requires-Dist: odoo (<12.1dev,>=12.0a)
